minexcel/__init__.py
minexcel/block.py
minexcel/utils.py
minexcel-0.2.2.dist-info/WHEEL
minexcel-0.2.2.dist-info/entry_points.txt
minexcel-0.2.2.dist-info/METADATA
minexcel-0.2.2.dist-info/RECORD
