Metadata-Version: 2.3
Name: minexcel
Version: 0.2.2
Summary: Add your description here
Requires-Dist: openpyxl>=3.1.5
Requires-Dist: pandas>=2.3.1
Requires-Python: >=3.10
Project-URL: Docs, https://william-swl.github.io/minexcel
Project-URL: Github, https://github.com/william-swl/minexcel
